{"states":[{"after":{"events":[{"id":1,"name":"Time","p":[{"id":1,"name":"Interval","v":{"k":2,"v":null}},{"id":2,"name":"Repeat","v":{"k":10,"v":false}}],"r":{"1":{"bh":true,"c":[{"command":[8,"",-1,0,0,1,"end sequence"],"kind":1},{"command":[3,11,0,3,13,0,12,20,12,21,12,50,12,100,12,0,0],"kind":35},{"command":[8,"Tumble",-1,0,0,1,"How, how were you able to do it?"],"kind":1},{"command":[3,13],"kind":37},{"command":[3,13,0,3,9,0,12,20,12,21,12,50,12,100,12,0,0],"kind":35},{"command":[8,"Luna",-1,0,0,1,"It doesn't matter how."],"kind":1},{"command":[8,"Luna",-1,0,0,1,"I want the truth!"],"kind":1},{"command":[3,9],"kind":37},{"command":[3,16,0,3,12,0,12,20,12,21,12,50,12,100,12,0,0],"kind":35},{"command":[8,"Tumble",-1,0,0,1,"Stay away from my family!!!"],"kind":1},{"command":[3,12],"kind":37},{"command":[3,10,0,3,7,0,12,20,12,21,12,50,12,100,12,0,0],"kind":35},{"command":[8,"Luna",-1,0,0,1,"Family?!"],"kind":1},{"command":[3,7],"kind":37},{"command":[3,32,0,3,-20,0,12,0,12,0,12,50,12,100,12,0,0],"kind":35},{"command":[8,"Tumble",-1,0,0,1,"This is what I've been protecting from the space walkers."],"kind":1},{"command":[8,"Tumble",-1,0,0,1,"They captured us, bred and sold us among the stars. "],"kind":1},{"command":[8,"Tumble",-1,0,0,1,"I know that is what you have come here to do."],"kind":1},{"command":[3,20],"kind":37},{"command":[3,9,0,3,6,0,12,20,12,21,12,50,12,100,12,0,0],"kind":35},{"command":[8,"Luna",-1,0,0,1,"That's not true, Tumble. I'm nothing like them."],"kind":1},{"command":[3,6],"kind":37},{"command":[3,13,0,3,9,0,12,20,12,21,12,50,12,100,12,0,0],"kind":35},{"command":[8,"Luna",-1,0,0,1,"I promise, I willl do my best to protect your world."],"kind":1},{"command":[3,9],"kind":37},{"command":[3,11,0,3,13,0,12,20,12,21,12,50,12,100,12,0,0],"kind":35},{"command":[8,"Tumble",-1,0,0,1,"Really??"],"kind":1},{"command":[3,13],"kind":37},{"command":[3,4,0,3,13,0,12,20,12,21,12,50,12,100,12,0,0],"kind":35},{"command":[8,"Tumble",-1,0,0,1,"Will you really protect our world?"],"kind":1},{"command":[3,13],"kind":37},{"command":[],"kind":3}]}},"sys":true}],"hId":-1,"id":6,"name":"OBJ0006","ooepf":false,"states":[{"cam":false,"climb":false,"dir":false,"gid":-1,"gk":0,"id":1,"move":true,"name":"State 1","pix":false,"pos":false,"stop":false,"sx":{"k":12,"v":1},"sy":{"k":12,"v":1},"sz":{"k":12,"v":1},"through":false,"x":0,"y":0}]},"afterT":9,"before":{"events":[{"id":1,"name":"Time","p":[{"id":1,"name":"Interval","v":{"k":2,"v":null}},{"id":2,"name":"Repeat","v":{"k":10,"v":false}}],"r":{"1":{"bh":true,"c":[{"command":[8,"",-1,0,0,1,"end sequence"],"kind":1},{"command":[3,11,0,3,13,0,12,20,12,21,12,50,12,100,12,0,0],"kind":35},{"command":[8,"Tumble",-1,0,0,1,"How, how were you able to do it?"],"kind":1},{"command":[3,13],"kind":37},{"command":[3,13,0,3,9,0,12,20,12,21,12,50,12,100,12,0,0],"kind":35},{"command":[8,"Luna",-1,0,0,1,"It doesn't matter how."],"kind":1},{"command":[8,"Luna",-1,0,0,1,"I want the truth!"],"kind":1},{"command":[3,9],"kind":37},{"command":[3,16,0,3,12,0,12,20,12,21,12,50,12,100,12,0,0],"kind":35},{"command":[8,"Tumble",-1,0,0,1,"Stay away from my family!!!"],"kind":1},{"command":[3,12],"kind":37},{"command":[3,10,0,3,7,0,12,20,12,21,12,50,12,100,12,0,0],"kind":35},{"command":[8,"Luna",-1,0,0,1,"Family?!"],"kind":1},{"command":[3,7],"kind":37},{"command":[3,32,0,3,-20,0,12,0,12,0,12,50,12,100,12,0,0],"kind":35},{"command":[8,"Tumble",-1,0,0,1,"This is what I've been protecting from the space walkers."],"kind":1},{"command":[8,"Tumble",-1,0,0,1,"They captured us, bred and sold us among the stars. "],"kind":1},{"command":[8,"Tumble",-1,0,0,1,"I know that is what you have come here to do."],"kind":1},{"command":[3,20],"kind":37},{"command":[3,9,0,3,9,0,12,20,12,21,12,50,12,100,12,0,0],"kind":35},{"command":[8,"Luna",-1,0,0,1,"That's not true, Tumble. I'm nothing like them."],"kind":1},{"command":[3,9],"kind":37},{"command":[3,13,0,3,9,0,12,20,12,21,12,50,12,100,12,0,0],"kind":35},{"command":[8,"Luna",-1,0,0,1,"I promise, I willl do my best to protect your world."],"kind":1},{"command":[3,9],"kind":37},{"command":[3,11,0,3,13,0,12,20,12,21,12,50,12,100,12,0,0],"kind":35},{"command":[8,"Tumble",-1,0,0,1,"Really??"],"kind":1},{"command":[3,13],"kind":37},{"command":[],"kind":3}]}},"sys":true}],"hId":-1,"id":6,"name":"OBJ0006","ooepf":false,"states":[{"cam":false,"climb":false,"dir":false,"gid":-1,"gk":0,"id":1,"move":true,"name":"State 1","pix":false,"pos":false,"stop":false,"sx":{"k":12,"v":1},"sy":{"k":12,"v":1},"sz":{"k":12,"v":1},"through":false,"x":0,"y":0}]},"beforeT":9,"pos":[5,0,0,5,0]}]}